yz_tg_shared/__init__.py
yz_tg_shared/data_access/__init__.py
yz_tg_shared/data_access/repositories/__init__.py
yz_tg_shared/data_access/repositories/category_repository.py
yz_tg_shared/data_access/repositories/channel_repository.py
yz_tg_shared/data_access/repositories/message_repository.py
yz_tg_shared/domain/__init__.py
yz_tg_shared/domain/services/__init__.py
yz_tg_shared/domain/services/unit_of_work.py
yz_tg_shared/entities/__init__.py
yz_tg_shared/entities/base.py
yz_tg_shared/entities/category.py
yz_tg_shared/entities/channel.py
yz_tg_shared/entities/message.py
yz_tg_shared/models/__init__.py
yz_tg_shared/models/category_model.py
yz_tg_shared/models/channel_model.py
yz_tg_shared/models/message_model.py
yz_tg_shared-1.0.9.dist-info/LICENSE
yz_tg_shared-1.0.9.dist-info/METADATA
yz_tg_shared-1.0.9.dist-info/WHEEL
yz_tg_shared-1.0.9.dist-info/top_level.txt
yz_tg_shared-1.0.9.dist-info/RECORD
